<gconfentryfile>
  <entrylist base="/apps/avant-window-navigator/effects">
    <entry>
      <key>active_background_icon</key>
      <schema_key>/schemas/apps/avant-window-navigator/effects/active_background_icon</schema_key>
      <value>
        <string></string>
      </value>
    </entry>
    <entry>
      <key>active_rect_color</key>
      <schema_key>/schemas/apps/avant-window-navigator/effects/active_rect_color</schema_key>
      <value>
        <string>#9090878779796666</string>
      </value>
    </entry>
    <entry>
      <key>active_rect_outline</key>
      <schema_key>/schemas/apps/avant-window-navigator/effects/active_rect_outline</schema_key>
      <value>
        <string>#0000000000000000</string>
      </value>
    </entry>
    <entry>
      <key>arrow_icon</key>
      <schema_key>/schemas/apps/avant-window-navigator/effects/arrow_icon</schema_key>
      <value>
        <string>__awn_internal_arrow2</string>
      </value>
    </entry>
    <entry>
      <key>dot_color</key>
      <schema_key>/schemas/apps/avant-window-navigator/effects/dot_color</schema_key>
      <value>
        <string>#4cccc443fffeff00</string>
      </value>
    </entry>
    <entry>
      <key>icon_alpha</key>
      <schema_key>/schemas/apps/avant-window-navigator/effects/icon_alpha</schema_key>
      <value>
        <float>1</float>
      </value>
    </entry>
    <entry>
      <key>icon_effect</key>
      <schema_key>/schemas/apps/avant-window-navigator/effects/icon_effect</schema_key>
      <value>
        <int>559240</int>
      </value>
    </entry>
    <entry>
      <key>reflection_alpha_multiplier</key>
      <schema_key>/schemas/apps/avant-window-navigator/effects/reflection_alpha_multiplier</schema_key>
      <value>
        <float>0.29999999999999999</float>
      </value>
    </entry>
    <entry>
      <key>reflection_offset</key>
      <schema_key>/schemas/apps/avant-window-navigator/effects/reflection_offset</schema_key>
      <value>
        <int>0</int>
      </value>
    </entry>
    <entry>
      <key>show_shadows</key>
      <schema_key>/schemas/apps/avant-window-navigator/effects/show_shadows</schema_key>
      <value>
        <bool>false</bool>
      </value>
    </entry>
  </entrylist>
  <entrylist base="/apps/avant-window-navigator/panel">
    <entry>
      <key>applet_list</key>
      <schema_key>/schemas/apps/avant-window-navigator/panel/applet_list</schema_key>
      <value>
        <list type="string">
            <value>
              <string>/usr/share/avant-window-navigator/applets/quick-prefs.desktop::1</string>
            </value>
            <value>
              <string>/usr/share/avant-window-navigator/applets/separator.desktop::2</string>
            </value>
            <value>
              <string>/usr/share/avant-window-navigator/applets/taskmanager.desktop::3</string>
            </value>
        </list>
      </value>
    </entry>
    <entry>
      <key>autohide</key>
      <schema_key>/schemas/apps/avant-window-navigator/panel/autohide</schema_key>
      <value>
        <int>0</int>
      </value>
    </entry>
    <entry>
      <key>clickthrough</key>
      <schema_key>/schemas/apps/avant-window-navigator/panel/clickthrough</schema_key>
      <value>
        <int>0</int>
      </value>
    </entry>
    <entry>
      <key>dialog_offset</key>
      <schema_key>/schemas/apps/avant-window-navigator/panel/dialog_offset</schema_key>
      <value>
        <int>15</int>
      </value>
    </entry>
    <entry>
      <key>expand</key>
      <schema_key>/schemas/apps/avant-window-navigator/panel/expand</schema_key>
      <value>
        <bool>false</bool>
      </value>
    </entry>
    <entry>
      <key>intellihide_mode</key>
      <schema_key>/schemas/apps/avant-window-navigator/panel/intellihide_mode</schema_key>
      <value>
        <int>2</int>
      </value>
    </entry>
    <entry>
      <key>monitor_align</key>
      <schema_key>/schemas/apps/avant-window-navigator/panel/monitor_align</schema_key>
      <value>
        <float>0.5</float>
      </value>
    </entry>
    <entry>
      <key>monitor_force</key>
      <schema_key>/schemas/apps/avant-window-navigator/panel/monitor_force</schema_key>
      <value>
        <bool>false</bool>
      </value>
    </entry>
    <entry>
      <key>monitor_height</key>
      <schema_key>/schemas/apps/avant-window-navigator/panel/monitor_height</schema_key>
      <value>
        <int>768</int>
      </value>
    </entry>
    <entry>
      <key>monitor_num</key>
      <schema_key>/schemas/apps/avant-window-navigator/panel/monitor_num</schema_key>
      <value>
        <int>-1</int>
      </value>
    </entry>
    <entry>
      <key>monitor_width</key>
      <schema_key>/schemas/apps/avant-window-navigator/panel/monitor_width</schema_key>
      <value>
        <int>1024</int>
      </value>
    </entry>
    <entry>
      <key>monitor_x_offset</key>
      <schema_key>/schemas/apps/avant-window-navigator/panel/monitor_x_offset</schema_key>
      <value>
        <int>0</int>
      </value>
    </entry>
    <entry>
      <key>monitor_y_offset</key>
      <schema_key>/schemas/apps/avant-window-navigator/panel/monitor_y_offset</schema_key>
      <value>
        <int>0</int>
      </value>
    </entry>
    <entry>
      <key>offset</key>
      <schema_key>/schemas/apps/avant-window-navigator/panel/offset</schema_key>
      <value>
        <int>10</int>
      </value>
    </entry>
    <entry>
      <key>orient</key>
      <schema_key>/schemas/apps/avant-window-navigator/panel/orient</schema_key>
      <value>
        <int>3</int>
      </value>
    </entry>
    <entry>
      <key>panel_mode</key>
      <schema_key>/schemas/apps/avant-window-navigator/panel/panel_mode</schema_key>
      <value>
        <bool>true</bool>
      </value>
    </entry>
    <entry>
      <key>size</key>
      <schema_key>/schemas/apps/avant-window-navigator/panel/size</schema_key>
      <value>
        <int>48</int>
      </value>
    </entry>
    <entry>
      <key>style</key>
      <schema_key>/schemas/apps/avant-window-navigator/panel/style</schema_key>
      <value>
        <int>1</int>
      </value>
    </entry>
    <entry>
      <key>ua_active_list</key>
      <schema_key>/schemas/apps/avant-window-navigator/panel/ua_active_list</schema_key>
      <value>
        <list type="string">
        </list>
      </value>
    </entry>
    <entry>
      <key>ua_list</key>
      <schema_key>/schemas/apps/avant-window-navigator/panel/ua_list</schema_key>
      <value>
        <list type="string">
        </list>
      </value>
    </entry>
  </entrylist>
  <entrylist base="/apps/avant-window-navigator/panels">
    <entry>
      <key>hide_delay</key>
      <schema_key>/schemas/apps/avant-window-navigator/panels/hide_delay</schema_key>
      <value>
        <int>500</int>
      </value>
    </entry>
    <entry>
      <key>mouse_poll_delay</key>
      <schema_key>/schemas/apps/avant-window-navigator/panels/mouse_poll_delay</schema_key>
      <value>
        <int>250</int>
      </value>
    </entry>
    <entry>
      <key>panel_list</key>
      <schema_key>/schemas/apps/avant-window-navigator/panels/panel_list</schema_key>
      <value>
        <list type="int">
            <value>
              <int>1</int>
            </value>
        </list>
      </value>
    </entry>
  </entrylist>
  <entrylist base="/apps/avant-window-navigator/shared">
    <entry>
      <key>allow_generic_config_edit</key>
      <schema_key>/schemas/apps/avant-window-navigator/shared/allow_generic_config_edit</schema_key>
      <value>
        <bool>false</bool>
      </value>
    </entry>
    <entry>
      <key>dialog_focus_loss_behavior</key>
      <schema_key>/schemas/apps/avant-window-navigator/shared/dialog_focus_loss_behavior</schema_key>
      <value>
        <bool>true</bool>
      </value>
    </entry>
    <entry>
      <key>long_press_timeout</key>
      <schema_key>/schemas/apps/avant-window-navigator/shared/long_press_timeout</schema_key>
      <value>
        <int>750</int>
      </value>
    </entry>
  </entrylist>
  <entrylist base="/apps/avant-window-navigator/theme">
    <entry>
      <key>border</key>
      <schema_key>/schemas/apps/avant-window-navigator/theme/border</schema_key>
      <value>
        <string>#e739e739e7398c8c</string>
      </value>
    </entry>
    <entry>
      <key>corner_radius</key>
      <schema_key>/schemas/apps/avant-window-navigator/theme/corner_radius</schema_key>
      <value>
        <float>16</float>
      </value>
    </entry>
    <entry>
      <key>current_theme</key>
      <schema_key>/schemas/apps/avant-window-navigator/theme/current_theme</schema_key>
      <value>
        <string>/usr/share/avant-window-navigator/themes/ZorinOS.awn-theme</string>
      </value>
    </entry>
    <entry>
      <key>curves_symmetry</key>
      <schema_key>/schemas/apps/avant-window-navigator/theme/curves_symmetry</schema_key>
      <value>
        <float>0.5</float>
      </value>
    </entry>
    <entry>
      <key>curviness</key>
      <schema_key>/schemas/apps/avant-window-navigator/theme/curviness</schema_key>
      <value>
        <float>1</float>
      </value>
    </entry>
    <entry>
      <key>dialog_bg</key>
      <schema_key>/schemas/apps/avant-window-navigator/theme/dialog_bg</schema_key>
      <value>
        <string>#f4f4f4f4f4f4ff00</string>
      </value>
    </entry>
    <entry>
      <key>dialog_gtk_mode</key>
      <schema_key>/schemas/apps/avant-window-navigator/theme/dialog_gtk_mode</schema_key>
      <value>
        <bool>true</bool>
      </value>
    </entry>
    <entry>
      <key>dialog_title_bg</key>
      <schema_key>/schemas/apps/avant-window-navigator/theme/dialog_title_bg</schema_key>
      <value>
        <string>#f9daf9daf9daff00</string>
      </value>
    </entry>
    <entry>
      <key>draw_pattern</key>
      <schema_key>/schemas/apps/avant-window-navigator/theme/draw_pattern</schema_key>
      <value>
        <bool>false</bool>
      </value>
    </entry>
    <entry>
      <key>floaty_offset</key>
      <schema_key>/schemas/apps/avant-window-navigator/theme/floaty_offset</schema_key>
      <value>
        <int>10</int>
      </value>
    </entry>
    <entry>
      <key>ghistep1</key>
      <schema_key>/schemas/apps/avant-window-navigator/theme/ghistep1</schema_key>
      <value>
        <string>#b3b3b3b3b3b36e6e</string>
      </value>
    </entry>
    <entry>
      <key>ghistep2</key>
      <schema_key>/schemas/apps/avant-window-navigator/theme/ghistep2</schema_key>
      <value>
        <string>#b39cb39cb39c6e6e</string>
      </value>
    </entry>
    <entry>
      <key>gstep1</key>
      <schema_key>/schemas/apps/avant-window-navigator/theme/gstep1</schema_key>
      <value>
        <string>#f4f4f4f4f4f4ffff</string>
      </value>
    </entry>
    <entry>
      <key>gstep2</key>
      <schema_key>/schemas/apps/avant-window-navigator/theme/gstep2</schema_key>
      <value>
        <string>#f4f4f4f4f4f4ffff</string>
      </value>
    </entry>
    <entry>
      <key>gtk_theme_mode</key>
      <schema_key>/schemas/apps/avant-window-navigator/theme/gtk_theme_mode</schema_key>
      <value>
        <bool>false</bool>
      </value>
    </entry>
    <entry>
      <key>hilight</key>
      <schema_key>/schemas/apps/avant-window-navigator/theme/hilight</schema_key>
      <value>
        <string>#0000aaaaffffffff</string>
      </value>
    </entry>
    <entry>
      <key>icon_font_mode</key>
      <schema_key>/schemas/apps/avant-window-navigator/theme/icon_font_mode</schema_key>
      <value>
        <int>2</int>
      </value>
    </entry>
    <entry>
      <key>icon_text_color</key>
      <schema_key>/schemas/apps/avant-window-navigator/theme/icon_text_color</schema_key>
      <value>
        <string>#1e1e1e1e1e1effff</string>
      </value>
    </entry>
    <entry>
      <key>icon_text_outline_color</key>
      <schema_key>/schemas/apps/avant-window-navigator/theme/icon_text_outline_color</schema_key>
      <value>
        <string>#ffffffffffff6464</string>
      </value>
    </entry>
    <entry>
      <key>icon_text_outline_width</key>
      <schema_key>/schemas/apps/avant-window-navigator/theme/icon_text_outline_width</schema_key>
      <value>
        <float>2.5</float>
      </value>
    </entry>
    <entry>
      <key>panel_angle</key>
      <schema_key>/schemas/apps/avant-window-navigator/theme/panel_angle</schema_key>
      <value>
        <float>45</float>
      </value>
    </entry>
    <entry>
      <key>pattern_alpha</key>
      <schema_key>/schemas/apps/avant-window-navigator/theme/pattern_alpha</schema_key>
      <value>
        <float>0.5</float>
      </value>
    </entry>
    <entry>
      <key>pattern_filename</key>
      <schema_key>/schemas/apps/avant-window-navigator/theme/pattern_filename</schema_key>
      <value>
        <string>None</string>
      </value>
    </entry>
    <entry>
      <key>sep_color</key>
      <schema_key>/schemas/apps/avant-window-navigator/theme/sep_color</schema_key>
      <value>
        <string>#ffffffffffff0000</string>
      </value>
    </entry>
    <entry>
      <key>show_sep</key>
      <schema_key>/schemas/apps/avant-window-navigator/theme/show_sep</schema_key>
      <value>
        <bool>true</bool>
      </value>
    </entry>
    <entry>
      <key>thickness</key>
      <schema_key>/schemas/apps/avant-window-navigator/theme/thickness</schema_key>
      <value>
        <float>0.1000000000000000</float>
      </value>
    </entry>
    <entry>
      <key>tooltip_bg_color</key>
      <schema_key>/schemas/apps/avant-window-navigator/theme/tooltip_bg_color</schema_key>
      <value>
        <string>#000000000000e0e0</string>
      </value>
    </entry>
    <entry>
      <key>tooltip_font_color</key>
      <schema_key>/schemas/apps/avant-window-navigator/theme/tooltip_font_color</schema_key>
      <value>
        <string>#ffffffffffffffff</string>
      </value>
    </entry>
    <entry>
      <key>tooltip_font_name</key>
      <schema_key>/schemas/apps/avant-window-navigator/theme/tooltip_font_name</schema_key>
      <value>
        <string>Ubuntu 11</string>
      </value>
    </entry>
    <entry>
      <key>tooltip_outline_color</key>
      <schema_key>/schemas/apps/avant-window-navigator/theme/tooltip_outline_color</schema_key>
      <value>
        <string>#0000000000005b5b</string>
      </value>
    </entry>
  </entrylist>
</gconfentryfile>
